Metadata-Version: 2.4
Name: proto-clickhouse-agent
Version: 1.0.5
Summary: ClickHouse AI Agent - Natural language interface for ClickHouse databases
Home-page: https://github.com/yourusername/proto
Author: Proto Team
Author-email: Proto Team <team@proto.dev>
Maintainer-email: Proto Team <team@proto.dev>
License-Expression: MIT
Project-URL: Homepage, https://github.com/vishprometa/proto
Project-URL: Documentation, https://proto.dev
Project-URL: Repository, https://github.com/vishprometa/proto
Project-URL: Issues, https://github.com/vishprometa/proto/issues
Project-URL: Changelog, https://github.com/vishprometa/proto/releases
Keywords: clickhouse,ai,agent,database,sql,nlp
Classifier: Development Status :: 4 - Beta
Classifier: Intended Audience :: Developers
Classifier: Intended Audience :: System Administrators
Classifier: Operating System :: OS Independent
Classifier: Programming Language :: Python :: 3
Classifier: Programming Language :: Python :: 3.8
Classifier: Programming Language :: Python :: 3.9
Classifier: Programming Language :: Python :: 3.10
Classifier: Programming Language :: Python :: 3.11
Classifier: Programming Language :: Python :: 3.12
Classifier: Topic :: Database
Classifier: Topic :: Scientific/Engineering :: Information Analysis
Classifier: Topic :: Software Development :: Libraries :: Python Modules
Requires-Python: >=3.8
Requires-Dist: typer[all]>=0.9.0
Requires-Dist: rich>=13.0.0
Requires-Dist: textual>=0.40.0
Requires-Dist: clickhouse-connect>=0.6.0
Requires-Dist: clickhouse-driver>=0.2.0
Requires-Dist: pandas>=1.5.0
Requires-Dist: numpy>=1.20.0
Requires-Dist: plotly>=5.0.0
Requires-Dist: matplotlib>=3.5.0
Requires-Dist: httpx>=0.24.0
Requires-Dist: requests>=2.28.0
Requires-Dist: python-dotenv>=1.0.0
Requires-Dist: pydantic>=2.0.0
Requires-Dist: aiofiles>=23.0.0
Requires-Dist: orjson>=3.8.0
Requires-Dist: structlog>=23.0.0
Requires-Dist: openai>=1.0.0
Requires-Dist: anthropic>=0.25.0
Requires-Dist: psutil>=5.8.0
Provides-Extra: dev
Requires-Dist: pytest>=7.0.0; extra == "dev"
Requires-Dist: pytest-asyncio>=0.21.0; extra == "dev"
Requires-Dist: black>=23.0.0; extra == "dev"
Requires-Dist: isort>=5.12.0; extra == "dev"
Requires-Dist: flake8>=6.0.0; extra == "dev"
Requires-Dist: mypy>=1.0.0; extra == "dev"
Dynamic: author
Dynamic: home-page
Dynamic: requires-python
